Metadata-Version: 2.1
Name: i3d-jax
Version: 0.0.1
Summary: I3D in Jax
Home-page: https://github.com/wilson1yan/i3d-jax
Author: Wilson Yan
Author-email: wilson1.yan@berkeley.edu
Classifier: Programming Language :: Python :: 3
Classifier: License :: OSI Approved :: BSD License
Classifier: Operating System :: OS Independent
License-File: LICENSE.md
